amplitude_client/__init__.py
amplitude_client/logger.py
amplitude_client/resources/__init__.py
amplitude_client/resources/schema.json
amplitude_client-0.1.4.dist-info/LICENSE
amplitude_client-0.1.4.dist-info/WHEEL
amplitude_client-0.1.4.dist-info/METADATA
amplitude_client-0.1.4.dist-info/RECORD
